rivet/__init__.py
rivet/_version.py
rivet/config.py
rivet/inform.py
rivet/s3_client_config.py
rivet/s3_copy.py
rivet/s3_delete.py
rivet/s3_list.py
rivet/s3_path_utils.py
rivet/s3_progressbar.py
rivet/s3_read.py
rivet/s3_write.py
rivet/storage_formats.py
rivet-1.6.0.dist-info/LICENSE.md
rivet-1.6.0.dist-info/METADATA
rivet-1.6.0.dist-info/WHEEL
rivet-1.6.0.dist-info/top_level.txt
rivet-1.6.0.dist-info/RECORD
