Metadata-Version: 2.1
Name: rivet
Version: 1.6.0
Summary: A Python-to-S3 interface with added convenience features.
Home-page: https://github.com/neighborhoods/rivet
Author: George Wood (@Geoiv)
Author-email: george.wood@55places.com
License: UNKNOWN
Platform: UNKNOWN
Requires-Dist: boto3 (>=1.10.0)
Requires-Dist: pandas (>=0.25.3)
Requires-Dist: pandavro (>=1.6)
Requires-Dist: pyarrow (>=3.0.0)
